ThreeHingeArch/__init__.py
ThreeHingedArch/__init__.py
ThreeHingedArch-0.0.4.dist-info/LICENSE
ThreeHingedArch-0.0.4.dist-info/METADATA
ThreeHingedArch-0.0.4.dist-info/WHEEL
ThreeHingedArch-0.0.4.dist-info/top_level.txt
ThreeHingedArch-0.0.4.dist-info/RECORD
