Metadata-Version: 2.1
Name: ThreeHingedArch
Version: 0.0.4
Summary: Static analysis of three heinged arches
Home-page: https://github.com/giboul/ThreeHingeArch
Author: giboul
Author-email: axel.giboulot@epfl.ch
License: MIT
Requires-Python: >=3.8
License-File: LICENSE
